Metadata-Version: 1.1
Name: easy-property
Version: 0.0.5
Summary: easy_property
Home-page: https://github.com/salabim/easy_property
Author: Ruud van der Ham
Author-email: info@salabim.org
License: UNKNOWN
Download-URL: https://github.com/salabim/easy_property
Keywords: property,addon
Platform: UNKNOWN
